grimoirelab_toolkit/__init__.py
grimoirelab_toolkit/_version.py
grimoirelab_toolkit/credential_manager/__init__.py
grimoirelab_toolkit/credential_manager/__main__.py
grimoirelab_toolkit/credential_manager/bw_manager.py
grimoirelab_toolkit/credential_manager/exceptions.py
grimoirelab_toolkit/datetime.py
grimoirelab_toolkit/identities.py
grimoirelab_toolkit/introspect.py
grimoirelab_toolkit/uris.py
grimoirelab_toolkit-1.2.4.dist-info/METADATA
grimoirelab_toolkit-1.2.4.dist-info/WHEEL
grimoirelab_toolkit-1.2.4.dist-info/licenses/AUTHORS
grimoirelab_toolkit-1.2.4.dist-info/licenses/LICENSE
grimoirelab_toolkit-1.2.4.dist-info/RECORD
