Metadata-Version: 2.4
Name: grimoirelab-toolkit
Version: 1.2.4
Summary: Toolkit of common functions used across GrimoireLab
License: GPL-3.0+
License-File: AUTHORS
License-File: LICENSE
Keywords: development,grimoirelab
Author: GrimoireLab Developers
Requires-Python: >=3.10,<4.0
Classifier: Development Status :: 5 - Production/Stable
Classifier: Intended Audience :: Developers
Classifier: License :: OSI Approved :: GNU General Public License v3 or later (GPLv3+)
Classifier: Programming Language :: Python :: 3
Classifier: Programming Language :: Python :: 3.10
Classifier: Programming Language :: Python :: 3.11
Classifier: Programming Language :: Python :: 3.12
Classifier: Programming Language :: Python :: 3.13
Classifier: Programming Language :: Python :: 3.14
Classifier: Topic :: Software Development
Requires-Dist: python-dateutil (>=2.8.2,<3.0.0)
Project-URL: Homepage, https://chaoss.github.io/grimoirelab/
Project-URL: Repository, https://github.com/chaoss/grimoirelab-toolkit
